ratd/__init__.py
ratd/reg_settings.py
ratd/api/__init__.py
ratd/cliargs/__init__.py
ratd/lib/__init__.py
ratd/utils/__init__.py
robust_atd-0.5.2.data/scripts/robust-convict.py
robust_atd-0.5.2.data/scripts/robust-profiles.py
robust_atd-0.5.2.data/scripts/robust-reporter.py
robust_atd-0.5.2.data/scripts/robust-search.py
robust_atd-0.5.2.data/scripts/robust-version-checker.py
robust_atd-0.5.2.data/scripts/robust-watchdog.py
robust_atd-0.5.2.data/scripts/robust.py
robust_atd-0.5.2.dist-info/DESCRIPTION.rst
robust_atd-0.5.2.dist-info/METADATA
robust_atd-0.5.2.dist-info/RECORD
robust_atd-0.5.2.dist-info/WHEEL
robust_atd-0.5.2.dist-info/metadata.json
robust_atd-0.5.2.dist-info/top_level.txt
