Metadata-Version: 2.0
Name: robust-atd
Version: 0.5.2
Summary: Manipulate McAfee ATD appliance
Home-page: http://github.com/shadowbq/robust-atd
Author: Shadowbq
Author-email: shadowbq@gmail.com
License: MIT
Keywords: atd mcafee ioc
Platform: UNKNOWN
Classifier: Development Status :: 4 - Beta
Classifier: Intended Audience :: System Administrators
Classifier: Topic :: Security
Classifier: License :: OSI Approved :: MIT License
Classifier: Programming Language :: Python :: 2 :: Only
Classifier: Programming Language :: Python :: 2.6
Classifier: Programming Language :: Python :: 2.7
Requires-Python: >=2.6, !=3.*
Provides-Extra: test
Provides-Extra: docs
Provides-Extra: dev
Requires-Dist: PyYAML
Requires-Dist: argparse
Requires-Dist: pathtools
Requires-Dist: urllib3
Requires-Dist: requests (==2.7.0)
Requires-Dist: watchdog (==0.8.3)
Provides-Extra: dev
Requires-Dist: rednose; extra == 'dev'
Requires-Dist: nose; extra == 'dev'
Requires-Dist: nose-regression; extra == 'dev'
Requires-Dist: nose-watch; extra == 'dev'
Requires-Dist: coverage; extra == 'dev'
Requires-Dist: flake8; extra == 'dev'
Requires-Dist: pep8-naming; extra == 'dev'
Requires-Dist: tox; extra == 'dev'
Requires-Dist: invoke; extra == 'dev'
Requires-Dist: HTTPretty; extra == 'dev'
Requires-Dist: vcrpy; extra == 'dev'
Requires-Dist: twine; extra == 'dev'
Provides-Extra: docs
Requires-Dist: Sphinx (==1.2.1); extra == 'docs'
Requires-Dist: sphinxcontrib-napoleon (==0.2.4); extra == 'docs'
Provides-Extra: test
Requires-Dist: nose (==1.3.0); extra == 'test'
Requires-Dist: tox (==1.6.1); extra == 'test'
